jarbin_toolkit_console/__init__.py
jarbin_toolkit_console/config.ini
jarbin_toolkit_console/console.py
jarbin_toolkit_console/ANSI/__init__.py
jarbin_toolkit_console/ANSI/ansi.py
jarbin_toolkit_console/ANSI/basepack.py
jarbin_toolkit_console/ANSI/color.py
jarbin_toolkit_console/ANSI/cursor.py
jarbin_toolkit_console/ANSI/line.py
jarbin_toolkit_console/Animation/__init__.py
jarbin_toolkit_console/Animation/animation.py
jarbin_toolkit_console/Animation/basepack.py
jarbin_toolkit_console/Animation/progressbar.py
jarbin_toolkit_console/Animation/spinner.py
jarbin_toolkit_console/Animation/style.py
jarbin_toolkit_console/System/__init__.py
jarbin_toolkit_console/System/setting.py
jarbin_toolkit_console/Text/__init__.py
jarbin_toolkit_console/Text/format.py
jarbin_toolkit_console/Text/text.py
jarbin_toolkit_console-0.1.0.0.dist-info/licenses/LICENSE
jarbin_toolkit_console-0.1.0.0.dist-info/METADATA
jarbin_toolkit_console-0.1.0.0.dist-info/WHEEL
jarbin_toolkit_console-0.1.0.0.dist-info/top_level.txt
jarbin_toolkit_console-0.1.0.0.dist-info/RECORD
